PyFaceGen/__init__.py
PyFaceGen/Alignment/NRICP.py
PyFaceGen/Alignment/NRICP_v2.py
PyFaceGen/Alignment/RigidAlignment.py
PyFaceGen/Alignment/__init__.py
PyFaceGen/Alignment/landmarks.py
PyFaceGen/Alignment/texture_transfer.py
PyFaceGen/Expression/DeformationTransfer.py
PyFaceGen/Expression/__init__.py
PyFaceGen/IO/__init__.py
PyFaceGen/IO/ply_loader.py
PyFaceGen/IO/pyassimp_loader.py
PyFaceGen/IO/wobj_loader.py
PyFaceGen/Mesh/GetComponents.py
PyFaceGen/Mesh/Graph.py
PyFaceGen/Mesh/Mesh.py
PyFaceGen/Mesh/Utils.py
PyFaceGen/Mesh/__init__.py
PyFaceGen/Tests/__init__.py
PyFaceGen/Tests/alignment_tests.py
PyFaceGen/Tests/iotests.py
PyFaceGen/Tests/mesh_tests.py
PyFaceGen/Visualisation/__init__.py
pyfacegen-0.1.7.dist-info/METADATA
pyfacegen-0.1.7.dist-info/WHEEL
pyfacegen-0.1.7.dist-info/__init__ (copy).py
pyfacegen-0.1.7.dist-info/top_level.txt
pyfacegen-0.1.7.dist-info/RECORD
