Metadata-Version: 2.1
Name: pyfacegen
Version: 0.1.7
Summary: A mesh library for python
Home-page: https://github.com/jsaunders909/PyFaceGen
Author: Jack Saunders
Author-email: jrs68@bath.ac.uk
License: UNKNOWN
Platform: UNKNOWN
Classifier: Programming Language :: Python :: 3
Classifier: License :: OSI Approved :: MIT License
Classifier: Operating System :: OS Independent
Requires-Python: >=3.6
